slope/__init__.py
slope/core.py
slope/nn.py
slope/operators.py
slope/procedures.py
slope/shapes.py
slope/backends/_numpy.py
slope/backends/iree.py
slope/backends/numpy.py
slope/backends/onnxruntime.py
slope_ad-0.1.2.dist-info/METADATA
slope_ad-0.1.2.dist-info/WHEEL
slope_ad-0.1.2.dist-info/licenses/LICENSE
slope_ad-0.1.2.dist-info/RECORD
