Metadata-Version: 2.1
Name: slope-ad
Version: 0.1.2
Summary: slope AD
Project-URL: Homepage, https://github.com/radenmuaz/slope
Project-URL: Issues, https://github.com/radenmuaz/slope/issues
Author-email: Raden Muaz <raden.m.muaz@gmail.com>
License-File: LICENSE
Classifier: License :: OSI Approved :: MIT License
Classifier: Operating System :: OS Independent
Classifier: Programming Language :: Python :: 3
Requires-Python: >=3.8
Requires-Dist: iree-compiler==20231113.707
Requires-Dist: iree-runtime==20231113.707
Requires-Dist: mkdocs
Requires-Dist: numpy
Requires-Dist: onnx
Requires-Dist: onnxruntime
Requires-Dist: pdoc
Requires-Dist: pygments
Requires-Dist: sympy
